filmtagger/__about__.py
filmtagger/__init__.py
filmtagger/cameras.toml
filmtagger/cli.py
filmtagger/films.toml
filmtagger-0.3.0.dist-info/METADATA
filmtagger-0.3.0.dist-info/WHEEL
filmtagger-0.3.0.dist-info/entry_points.txt
filmtagger-0.3.0.dist-info/licenses/LICENSE
filmtagger-0.3.0.dist-info/RECORD
