Metadata-Version: 2.4
Name: filmtagger
Version: 0.3.0
Summary: A simple CLI to tag film scans with EXIF metadata
Project-URL: Homepage, https://github.com/2n3906/filmtagger
Project-URL: Repository, https://github.com/2n3906/filmtagger.git
Project-URL: Issues, https://github.com/2n3906/filmtagger/issues
Author-email: Scott Johnston <sjohnston@alum.mit.edu>
License-Expression: MIT
License-File: LICENSE
Keywords: exif,film,metadata,photography
Classifier: Development Status :: 4 - Beta
Classifier: Environment :: Console
Classifier: License :: OSI Approved :: MIT License
Classifier: Programming Language :: Python :: 3
Classifier: Programming Language :: Python :: 3.8
Classifier: Programming Language :: Python :: 3.9
Classifier: Programming Language :: Python :: 3.10
Classifier: Programming Language :: Python :: 3.11
Classifier: Programming Language :: Python :: 3.12
Requires-Python: >=3.8
Requires-Dist: click>=8.0.0
Requires-Dist: fuzzywuzzy>=0.18.0
Requires-Dist: importlib-resources>=5.0.0; python_version < '3.9'
Requires-Dist: pyexiv2>=2.8.0
Requires-Dist: python-dateutil>=2.8.0
Requires-Dist: python-levenshtein>=0.21.0
Requires-Dist: tomli>=1.2.0
